antenna_intensity_modeler/__init__.py
antenna_intensity_modeler/cli.py
antenna_intensity_modeler/parabolic.py
antenna_intensity_modeler-0.1.1.dist-info/LICENSE
antenna_intensity_modeler-0.1.1.dist-info/WHEEL
antenna_intensity_modeler-0.1.1.dist-info/METADATA
antenna_intensity_modeler-0.1.1.dist-info/RECORD
